MANIFEST.in
README.txt
setup.cfg
setup.py
docs/HISTORY.txt
horae/__init__.py
horae.autocomplete.egg-info/PKG-INFO
horae.autocomplete.egg-info/SOURCES.txt
horae.autocomplete.egg-info/dependency_links.txt
horae.autocomplete.egg-info/entry_points.txt
horae.autocomplete.egg-info/namespace_packages.txt
horae.autocomplete.egg-info/not-zip-safe
horae.autocomplete.egg-info/requires.txt
horae.autocomplete.egg-info/top_level.txt
horae/autocomplete/__init__.py
horae/autocomplete/configure.zcml
horae/autocomplete/fields.py
horae/autocomplete/interfaces.py
horae/autocomplete/providers.py
horae/autocomplete/resource.py
horae/autocomplete/widgets.py
horae/autocomplete/static/autocomplete.css
horae/autocomplete/static/autocomplete.js