Metadata-Version: 1.0
Name: horae.autocomplete
Version: 1.0a1
Summary: Provides autocomplete fields and widgets for zope.formlib
Home-page: UNKNOWN
Author: Simon Kaeser
Author-email: skaeser@gmail.com
License: GPL
Platform: UNKNOWN
Classifier: Programming Language :: Python
